django_debug_toolbar_requests-1.0.5.dist-info/METADATA
django_debug_toolbar_requests-1.0.5.dist-info/RECORD
django_debug_toolbar_requests-1.0.5.dist-info/WHEEL
django_debug_toolbar_requests-1.0.5.dist-info/top_level.txt
requests_toolbar/__init__.py
requests_toolbar/operation_tracker.py
requests_toolbar/panels.py
requests_toolbar/templates/requests_toolbar/panels/requests.html
requests_toolbar/templatetags/__init__.py
requests_toolbar/templatetags/requests_toolbar_tags.py
