Metadata-Version: 2.1
Name: django-debug-toolbar-requests
Version: 1.0.5
Summary: Adds requests debuging information
Home-page: https://github.com/ENERGYLINX/django-debug-toolbar-requests
Author: Martin Voldrich
Author-email: rbas.cz@gmail.com
License: BSD 3-Clause License
Requires-Dist: requests
